nstrumenta/__init__.py
nstrumenta/client.py
nstrumenta/mcp_client.py
nstrumenta-4.2.5.dist-info/METADATA
nstrumenta-4.2.5.dist-info/WHEEL
nstrumenta-4.2.5.dist-info/top_level.txt
nstrumenta-4.2.5.dist-info/RECORD
